mdict_utils/__init__.py
mdict_utils/__main__.py
mdict_utils/about.py
mdict_utils/chtml.py
mdict_utils/reader.py
mdict_utils/utils.py
mdict_utils/writer.py
mdict_utils/base/__init__.py
mdict_utils/base/lzo.py
mdict_utils/base/pureSalsa20.py
mdict_utils/base/readmdict.py
mdict_utils/base/ripemd128.py
mdict_utils/base/writemdict.py
mdict_utils-1.3.12.dist-info/LICENSE
mdict_utils-1.3.12.dist-info/LICENSE.996ICU
mdict_utils-1.3.12.dist-info/METADATA
mdict_utils-1.3.12.dist-info/WHEEL
mdict_utils-1.3.12.dist-info/entry_points.txt
mdict_utils-1.3.12.dist-info/top_level.txt
mdict_utils-1.3.12.dist-info/RECORD
