Metadata-Version: 2.1
Name: mdict-utils
Version: 1.3.12
Summary: MDict pack/unpack tool
Home-page: https://github.com/liuyug/mdict-utils.git
Author-email: liuyug@gmail.com
License: MIT
Platform: noarch
Requires-Python: >=3.6
License-File: LICENSE
License-File: LICENSE.996ICU
Requires-Dist: tqdm
Requires-Dist: xxhash
